{"basicTests": {"00CDC421FA3BA07D": {"filename": "/system/lib64/libnfc_nci_jni.so", "substring": "125900276", "testType": "FILE_CONTAINS_SUBSTRING"}, "00F6BF63FF801026": {"filename": "/system/lib/libstagefright_soft_amrwbenc.so", "substring": "132647222", "testType": "FILE_CONTAINS_SUBSTRING"}, "02CCF870805B7870": {"filename": "/system/lib64/libnxpnfc_nci_jni.so", "substring": "phLibNfc_GetKeyNumberMFC returning = 0x%x Key = 0x%x", "testType": "FILE_CONTAINS_SUBSTRING"}, "04251F3EA780472D": {"filename": "/system/lib/libnfc_nci_jni.so", "substring": "132083376", "testType": "FILE_CONTAINS_SUBSTRING"}, "054875B0D500F6E3": {"filename": "/system/lib/libLGnfc_jni.so", "testType": "FILE_EXISTS"}, "0805C0085E831D29": {"filename": "/system/lib/libnfc_sec_jni.so", "substring": "125900276", "testType": "FILE_CONTAINS_SUBSTRING"}, "0B18DA3760DB7EB5": {"filename": "/system/lib64/libnfc_nci_jni_zte.so", "substring": "132082342", "testType": "FILE_CONTAINS_SUBSTRING"}, "0DC15BE312932B29": {"filename": "/system/lib64/libnfc_nci_jni_45_553.so", "substring": "132083376", "testType": "FILE_CONTAINS_SUBSTRING"}, "0FDB19F6054F8C5E": {"filename": "/system/lib/libnfc_nci_jni.so", "substring": "132082342", "testType": "FILE_CONTAINS_SUBSTRING"}, "15F1C4E462C880F2": {"filename": "/system/lib64/libnfc_nci_jni_45_553.so", "substring": "phLibNfc_GetKeyNumberMFC returning = 0x%x Key = 0x%x", "testType": "FILE_CONTAINS_SUBSTRING"}, "16649FC5FB0726D9": {"filename": "/system/lib64/libsn100nfc_nci_jni.so", "substring": "132083376", "testType": "FILE_CONTAINS_SUBSTRING"}, "1716EB015C01A939": {"filename": "/system/lib/libnfc_sec_jni.so", "testType": "FILE_EXISTS"}, "1A36F81CE38E6270": {"filename": "/system/lib64/libnfc_nci_jni_zte.so", "substring": "125900276", "testType": "FILE_CONTAINS_SUBSTRING"}, "1ACEF432C8A4C123": {"filename": "/system/lib/libstagefright_soft_amrwbenc.so", "substring": "b/132647222, OOB access in ind array track=%d i=%d", "testType": "FILE_CONTAINS_SUBSTRING"}, "1C9902CFEBC4DB46": {"filename": "/system/lib64/vndk-28/libbinder.so", "substring": "Status(%d): '", "testType": "FILE_CONTAINS_SUBSTRING"}, "1DA74639D458AFB5": {"filename": "/system/lib64/libnxpnfc_nci_jni.so", "testType": "FILE_EXISTS"}, "1F0CB92458C772DF": {"filename": "/system/lib/libnfc_nci_jni_45_551.so", "testType": "FILE_EXISTS"}, "1F9806477B3E3DAF": {"filename": "/system/lib64/libsn100nfc_nci_jni.so", "substring": "phLibNfc_GetKeyNumberMFC returning = 0x%x Key = 0x%x", "testType": "FILE_CONTAINS_SUBSTRING"}, "1FEA582A4E188291": {"filename": "/system/lib64/libnfc_nci_jni_45_551.so", "testType": "FILE_EXISTS"}, "24A408D9DCFB4010": {"filename": "/system/lib64/libnfc_nci_jni_45_551.so", "substring": "125900276", "testType": "FILE_CONTAINS_SUBSTRING"}, "289FC709C2BFAE11": {"filename": "/system/lib64/libLGnfc_jni.so", "testType": "FILE_EXISTS"}, "2AC9CB5D7E47F7B5": {"filename": "/system/lib/vndk-28/libbinder.so", "substring": "132650049", "testType": "FILE_CONTAINS_SUBSTRING"}, "2B7A1943B7C16292": {"filename": "/system/lib64/libnfc_nci_jni_45_553.so", "testType": "FILE_EXISTS"}, "2CC5F14367ED6C9A": {"filename": "/system/lib64/libnqnfc_nci_jni.so", "testType": "FILE_EXISTS"}, "313088ED697C5A38": {"filename": "/system/lib/libLGnfc_jni.so", "substring": "phLibNfc_GetKeyNumberMFC returning = 0x%x Key = 0x%x", "testType": "FILE_CONTAINS_SUBSTRING"}, "3D269A36DC539512": {"filename": "/system/lib64/libLGnfc_jni.so", "substring": "132083376", "testType": "FILE_CONTAINS_SUBSTRING"}, "42FFA396DD5155FF": {"filename": "/system/lib64/libnfc_nci_jni_45_551.so", "substring": "132083376", "testType": "FILE_CONTAINS_SUBSTRING"}, "43795AC52AC27CF5": {"filename": "/system/lib64/libnqnfc_nci_jni.so", "substring": "125900276", "testType": "FILE_CONTAINS_SUBSTRING"}, "4A4B3B02649C9E55": {"filename": "/system/lib64/libnfc_nci_jni_zte.so", "testType": "FILE_EXISTS"}, "4CD29609FBE33129": {"filename": "/system/lib64/libnxpnfc_nci_jni.so", "substring": "132082342", "testType": "FILE_CONTAINS_SUBSTRING"}, "533EFA5FF66D204C": {"filename": "/system/vendor/lib64/libnfc_nci_jni.so", "substring": "phLibNfc_GetKeyNumberMFC returning = 0x%x Key = 0x%x", "testType": "FILE_CONTAINS_SUBSTRING"}, "583E0A0B11AE7888": {"filename": "/system/lib64/libLGnfc_jni.so", "substring": "125900276", "testType": "FILE_CONTAINS_SUBSTRING"}, "59EA273C099F5C7E": {"filename": "/system/lib64/libnfc_nci_jni.so", "substring": "phLibNfc_GetKeyNumberMFC returning = 0x%x Key = 0x%x", "testType": "FILE_CONTAINS_SUBSTRING"}, "5BD25B65EE4C0E73": {"filename": "/system/lib64/libnqnfc_nci_jni.so", "substring": "132083376", "testType": "FILE_CONTAINS_SUBSTRING"}, "5D89FB87FE4AC5C5": {"filename": "/system/lib64/libnfc_nci_jni_zte.so", "substring": "132083376", "testType": "FILE_CONTAINS_SUBSTRING"}, "5F2251703B4619AF": {"filename": "/system/vendor/lib/libstagefright_soft_c2amrwbenc.so", "substring": "b/132647222, OOB access in ind array track=%d i=%d", "testType": "FILE_CONTAINS_SUBSTRING"}, "6376324F1C0CAF22": {"filename": "/system/vendor/lib/libbinder.so", "substring": "132650049", "testType": "FILE_CONTAINS_SUBSTRING"}, "63EB1EF017A89320": {"filename": "/system/lib64/libnqnfc_nci_jni.so", "substring": "132082342", "testType": "FILE_CONTAINS_SUBSTRING"}, "662F7B714A630898": {"filename": "/system/vendor/lib/libstagefright_soft_c2amrwbenc.so", "symbol": "cor_h_vec_012", "testType": "BINARY_CONTAINS_SYMBOL"}, "69445E8033BE30AF": {"filename": "/system/lib64/libnfc_nci_jni.so", "substring": "132083376", "testType": "FILE_CONTAINS_SUBSTRING"}, "69A42F2F356A9B5D": {"filename": "/system/lib64/libsn100nfc_nci_jni.so", "testType": "FILE_EXISTS"}, "6BC3A3FAAD7DBCCA": {"filename": "/system/vendor/lib/libstagefright_soft_c2amrwbenc.so", "testType": "FILE_EXISTS"}, "6C34A181E3802579": {"filename": "/system/lib/vndk-28/libstagefright_soft_amrwbenc.so", "testType": "FILE_EXISTS"}, "6F5740DB85FA8744": {"filename": "/system/lib/libnfc_sec_jni.so", "substring": "132082342", "testType": "FILE_CONTAINS_SUBSTRING"}, "7193C995016012A1": {"filename": "/system/lib/libstagefright_soft_amrwbenc.so", "symbol": "cor_h_vec_012", "testType": "BINARY_CONTAINS_SYMBOL"}, "740EF6B7A2FB4966": {"filename": "/system/lib64/libnxpnfc_nci_jni.so", "substring": "132083376", "testType": "FILE_CONTAINS_SUBSTRING"}, "76C8077CD880B39B": {"filename": "/system/lib64/libnfc_nci_jni_zte.so", "substring": "phLibNfc_GetKeyNumberMFC returning = 0x%x Key = 0x%x", "testType": "FILE_CONTAINS_SUBSTRING"}, "7C2B6C6F1B24CAB7": {"filename": "/system/lib/vndk-28/libbinder.so", "testType": "FILE_EXISTS"}, "7D316FB5ACEEA609": {"filename": "/system/lib64/libstagefright_soft_amrwbenc.so", "substring": "132647222", "testType": "FILE_CONTAINS_SUBSTRING"}, "7F4961588F8A2E91": {"filename": "/system/lib64/libnfc_sec_jni.so", "substring": "132083376", "testType": "FILE_CONTAINS_SUBSTRING"}, "82020C8F2966AF2B": {"filename": "/system/lib64/libnqnfc_nci_jni.so", "substring": "phLibNfc_GetKeyNumberMFC returning = 0x%x Key = 0x%x", "testType": "FILE_CONTAINS_SUBSTRING"}, "83E35F58F83E47EA": {"filename": "/system/lib64/libnfc_nci_jni_45_551.so", "substring": "phLibNfc_GetKeyNumberMFC returning = 0x%x Key = 0x%x", "testType": "FILE_CONTAINS_SUBSTRING"}, "88905B681C4A3F7A": {"filename": "/system/lib64/vndk-28/libbinder.so", "substring": "132650049", "testType": "FILE_CONTAINS_SUBSTRING"}, "8A0C573AE03C7F90": {"filename": "/system/vendor/lib64/libnfc_nci_jni.so", "testType": "FILE_EXISTS"}, "8A7D0592ED6DB3C5": {"filename": "/system/lib/libnfc_nci_jni.so", "testType": "FILE_EXISTS"}, "8DC1DD155B97A455": {"filename": "/system/lib/libLGnfc_jni.so", "substring": "125900276", "testType": "FILE_CONTAINS_SUBSTRING"}, "8DF6F0EBF0EAB8E5": {"filename": "/system/lib/vndk-28/libstagefright_soft_amrwbenc.so", "substring": "132647222", "testType": "FILE_CONTAINS_SUBSTRING"}, "8E7A4334F40DE6BE": {"filename": "/system/vendor/lib64/libnfc_nci_jni.so", "substring": "125900276", "testType": "FILE_CONTAINS_SUBSTRING"}, "932FC152256D05FA": {"filename": "/system/lib64/libstagefright_soft_amrwbenc.so", "substring": "b/132647222, OOB access in ind array track=%d i=%d", "testType": "FILE_CONTAINS_SUBSTRING"}, "9721C1AB55B2447F": {"filename": "/system/lib64/libstagefright_soft_amrwbenc.so", "symbol": "cor_h_vec_012", "testType": "BINARY_CONTAINS_SYMBOL"}, "9957FD6FF00DB00B": {"filename": "/system/vendor/lib64/libnfc_nci_jni.so", "substring": "132083376", "testType": "FILE_CONTAINS_SUBSTRING"}, "9DCF8661059888DC": {"filename": "/system/lib/vndk-28/libstagefright_soft_amrwbenc.so", "symbol": "cor_h_vec_012", "testType": "BINARY_CONTAINS_SYMBOL"}, "9EBAFDAF093C596F": {"filename": "/system/lib/libnfc_nci_jni_45_551.so", "substring": "phLibNfc_GetKeyNumberMFC returning = 0x%x Key = 0x%x", "testType": "FILE_CONTAINS_SUBSTRING"}, "A3F80446C10ECE13": {"filename": "/system/vendor/lib64/libnfc_nci_jni.so", "substring": "132082342", "testType": "FILE_CONTAINS_SUBSTRING"}, "A7DF461D70ADCEAE": {"filename": "/system/lib/libnfc_sec_jni.so", "substring": "132083376", "testType": "FILE_CONTAINS_SUBSTRING"}, "A7FE4CB9139C75F9": {"filename": "/system/lib64/libnfc_nci_jni.so", "testType": "FILE_EXISTS"}, "AA9FDE1F7348AC78": {"filename": "/system/lib64/libnfc_nci_jni_45_553.so", "substring": "132082342", "testType": "FILE_CONTAINS_SUBSTRING"}, "AAD48C255080CA0A": {"filename": "/system/lib64/libstagefright_soft_amrwbenc.so", "testType": "FILE_EXISTS"}, "AC50274A2F01492F": {"filename": "/system/lib/libLGnfc_jni.so", "substring": "132082342", "testType": "FILE_CONTAINS_SUBSTRING"}, "B063F1BFF141E0E6": {"filename": "/system/vendor/lib/libbinder.so", "testType": "FILE_EXISTS"}, "B07A8DB1184541B3": {"filename": "/system/lib/vndk-28/libbinder.so", "substring": "Status(%d): '", "testType": "FILE_CONTAINS_SUBSTRING"}, "B2AD904DD2FCE297": {"filename": "/system/lib64/vndk-28/libbinder.so", "testType": "FILE_EXISTS"}, "B37C67F4AFA397F7": {"filename": "/system/lib/libnfc_nci_jni_45_551.so", "substring": "125900276", "testType": "FILE_CONTAINS_SUBSTRING"}, "B6EFAD7EB5614500": {"filename": "/system/lib/libnfc_nci_jni_45_551.so", "substring": "132083376", "testType": "FILE_CONTAINS_SUBSTRING"}, "C91A743855171C30": {"filename": "/system/lib64/libnfc_sec_jni.so", "substring": "125900276", "testType": "FILE_CONTAINS_SUBSTRING"}, "C969CE66DFF2ADFE": {"filename": "/system/lib/libnfc_nci_jni_45_551.so", "substring": "132082342", "testType": "FILE_CONTAINS_SUBSTRING"}, "CAD095697F8D1AF9": {"filename": "/system/lib64/libsn100nfc_nci_jni.so", "substring": "132082342", "testType": "FILE_CONTAINS_SUBSTRING"}, "CBDAFAA0384B2604": {"filename": "/system/lib64/libnfc_nci_jni_45_553.so", "substring": "125900276", "testType": "FILE_CONTAINS_SUBSTRING"}, "CFBB69BD3B997D4E": {"filename": "/system/lib/libnfc_nci_jni.so", "substring": "125900276", "testType": "FILE_CONTAINS_SUBSTRING"}, "D04ED6729A86E5B5": {"filename": "/system/lib64/libnxpnfc_nci_jni.so", "substring": "125900276", "testType": "FILE_CONTAINS_SUBSTRING"}, "D9443716A90C7666": {"filename": "/system/lib64/libsn100nfc_nci_jni.so", "substring": "125900276", "testType": "FILE_CONTAINS_SUBSTRING"}, "DA98513CFB010631": {"filename": "/system/vendor/lib/libstagefright_soft_c2amrwbenc.so", "substring": "132647222", "testType": "FILE_CONTAINS_SUBSTRING"}, "E3F87A8339DBF0A8": {"filename": "/system/lib64/libLGnfc_jni.so", "substring": "phLibNfc_GetKeyNumberMFC returning = 0x%x Key = 0x%x", "testType": "FILE_CONTAINS_SUBSTRING"}, "E43E15014EC25A20": {"filename": "/system/lib64/libLGnfc_jni.so", "substring": "132082342", "testType": "FILE_CONTAINS_SUBSTRING"}, "E726B67E9356FEC6": {"filename": "/system/lib/libnfc_sec_jni.so", "substring": "phLibNfc_GetKeyNumberMFC returning = 0x%x Key = 0x%x", "testType": "FILE_CONTAINS_SUBSTRING"}, "E74C8DD1C40E8DD2": {"filename": "/system/lib64/libnfc_nci_jni_45_551.so", "substring": "132082342", "testType": "FILE_CONTAINS_SUBSTRING"}, "EAA82C281A7BA9E0": {"filename": "/system/lib/vndk-28/libstagefright_soft_amrwbenc.so", "substring": "b/132647222, OOB access in ind array track=%d i=%d", "testType": "FILE_CONTAINS_SUBSTRING"}, "EEA39AB5A6FF9F7F": {"filename": "/system/lib64/libnfc_sec_jni.so", "testType": "FILE_EXISTS"}, "F1C09FCEF65CC63F": {"filename": "/system/lib/libstagefright_soft_amrwbenc.so", "testType": "FILE_EXISTS"}, "F222EAD578B56A2F": {"filename": "/system/lib64/libnfc_sec_jni.so", "substring": "132082342", "testType": "FILE_CONTAINS_SUBSTRING"}, "F2AF31EB42A8A24F": {"filename": "/system/lib/libLGnfc_jni.so", "substring": "132083376", "testType": "FILE_CONTAINS_SUBSTRING"}, "F4A5938E5DAEECFC": {"filename": "/system/lib/libnfc_nci_jni.so", "substring": "phLibNfc_GetKeyNumberMFC returning = 0x%x Key = 0x%x", "testType": "FILE_CONTAINS_SUBSTRING"}, "F909C3E2ABC31A00": {"filename": "/system/vendor/lib/libbinder.so", "substring": "Status(%d): '", "testType": "FILE_CONTAINS_SUBSTRING"}, "FB954B1A14D849C4": {"filename": "/system/lib64/libnfc_sec_jni.so", "substring": "phLibNfc_GetKeyNumberMFC returning = 0x%x Key = 0x%x", "testType": "FILE_CONTAINS_SUBSTRING"}, "FC935BFD7770C5FB": {"filename": "/system/lib64/libnfc_nci_jni.so", "substring": "132082342", "testType": "FILE_CONTAINS_SUBSTRING"}}}